hyperpony/__init__.py
hyperpony/actions.py
hyperpony/client_state.py
hyperpony/client_state_tests.py
hyperpony/element.py
hyperpony/element_tests.py
hyperpony/form.py
hyperpony/form_tests.py
hyperpony/htmx.py
hyperpony/htmx_tests.py
hyperpony/htpy.py
hyperpony/inject_params.py
hyperpony/inject_params_tests.py
hyperpony/middleware.py
hyperpony/response_handler.py
hyperpony/static/hyperpony.js
hyperpony/static/hyperpony_swap_merge.js
hyperpony/templates/hyperpony/tests/TemplateResponse.html
hyperpony/templatetags/__init__.py
hyperpony/templatetags/hyperpony.py
hyperpony/testutils.py
hyperpony/utils.py
hyperpony/views.py
hyperpony/views_tests.py
hyperpony-0.79.0.dist-info/LICENSE
hyperpony-0.79.0.dist-info/METADATA
hyperpony-0.79.0.dist-info/WHEEL
hyperpony-0.79.0.dist-info/RECORD
