Metadata-Version: 2.3
Name: hyperpony
Version: 0.79.0
Summary: Django library for building web applications with htmx
License: MIT
Keywords: django,python
Author: Roman Roelofsen
Author-email: romanroe@gmail.com
Requires-Python: >=3.13
Classifier: License :: OSI Approved :: MIT License
Classifier: Programming Language :: Python :: 3
Classifier: Programming Language :: Python :: 3.13
Requires-Dist: django (>=4,<6)
Requires-Dist: django-htmx (>=1.14.0,<2.0.0)
Requires-Dist: django-ninja (>=1.2.1,<2.0.0)
Requires-Dist: htpy (>=24.12.0,<25.0.0)
Requires-Dist: lxml (>=5.1.0,<6.0.0)
Requires-Dist: orjson (>=3.10.6,<4.0.0)
Requires-Dist: pydantic (>=2.8.2,<3.0.0)
Requires-Dist: pytest-mock (>=3.14.0,<4.0.0)
Requires-Dist: wrapt (>=1.15.0,<2.0.0)
Project-URL: Repository, https://github.com/romanroe/hyperpony
